AUTHORS.md
HISTORY.md
LICENSE
MANIFEST.in
README.md
setup.py
django_reredirects.egg-info/PKG-INFO
django_reredirects.egg-info/SOURCES.txt
django_reredirects.egg-info/dependency_links.txt
django_reredirects.egg-info/not-zip-safe
django_reredirects.egg-info/requires.txt
django_reredirects.egg-info/top_level.txt
reredirects/__init__.py
reredirects/admin.py
reredirects/middleware.py
reredirects/models.py